html_gen/__init__.py
html_gen-0.0.2.dist-info/LICENSE
html_gen-0.0.2.dist-info/METADATA
html_gen-0.0.2.dist-info/WHEEL
html_gen-0.0.2.dist-info/top_level.txt
html_gen-0.0.2.dist-info/RECORD
