Metadata-Version: 2.1
Name: html-gen
Version: 0.0.2
Summary: A package to generate HTML from your code.
Home-page: https://github.com/regmicmahesh/hgen_python
Author: Mahesh C. Regmi
Author-email: regmicmahesh@gmail.com
License: UNKNOWN
Platform: UNKNOWN
Classifier: Programming Language :: Python :: 3
Classifier: License :: OSI Approved :: MIT License
Classifier: Operating System :: OS Independent
Requires-Python: >=3.6
